timescale_db_manager/__init__.py
timescale_db_manager/database_types/__init__.py
timescale_db_manager/database_types/cryptofeed.py
timescale_db_manager/utilities.py
timescale_db_manager-0.1.8.dist-info/METADATA
timescale_db_manager-0.1.8.dist-info/WHEEL
timescale_db_manager-0.1.8.dist-info/RECORD
