Metadata-Version: 2.1
Name: timescale-db-manager
Version: 0.1.8
Summary: 
Author: James Baber
Author-email: james.baber1@gmail.com
Requires-Python: >=3.9,<4.0.0
Classifier: Programming Language :: Python :: 3
Classifier: Programming Language :: Python :: 3.9
Classifier: Programming Language :: Python :: 3.10
Classifier: Programming Language :: Python :: 3.11
Classifier: Programming Language :: Python :: 3.12
Requires-Dist: boto3 (>=1.34.39)
Requires-Dist: pandas (>=2.2.0,<3.0.0)
Requires-Dist: psycopg2-binary (>=2.9.9,<3.0.0)
